llm_prompt_builders/__init__.py
llm_prompt_builders/accelerators/__init__.py
llm_prompt_builders/accelerators/chain.py
llm_prompt_builders/accelerators/parallel.py
llm_prompt_builders/accelerators/retry.py
llm_prompt_builders/config/__init__.py
llm_prompt_builders/config/defaults.py
llm_prompt_builders/connectors/__init__.py
llm_prompt_builders/connectors/openai_connector.py
llm_prompt_builders/contexts/__init__.py
llm_prompt_builders/contexts/healthcare_context.py
llm_prompt_builders/contexts/lifescience_context.py
llm_prompt_builders/contexts/research.py
llm_prompt_builders/evaluators/__init__.py
llm_prompt_builders/evaluators/semantic.py
llm_prompt_builders/pipelines/__init__.py
llm_prompt_builders/pipelines/analysis_pipeline.py
llm_prompt_builders/prompts/__init__.py
llm_prompt_builders/prompts/base.py
llm_prompt_builders/prompts/classification.py
llm_prompt_builders/prompts/cohort_logic.py
llm_prompt_builders/prompts/extraction.py
llm_prompt_builders/prompts/is_relevant.py
llm_prompt_builders/prompts/summarization.py
llm_prompt_builders/roles/__init__.py
llm_prompt_builders/roles/generic.py
llm_prompt_builders/roles/healthcare.py
llm_prompt_builders/roles/lifescience.py
llm_prompt_builders/schemas/__init__.py
llm_prompt_builders/schemas/models.py
llm_prompt_builders/templates/__init__.py
llm_prompt_builders/templates/question_template.py
llm_prompt_builders/utils/__init__.py
llm_prompt_builders/utils/stitcher.py
llm_prompt_builders-0.3.0.dist-info/METADATA
llm_prompt_builders-0.3.0.dist-info/WHEEL
llm_prompt_builders-0.3.0.dist-info/entry_points.txt
llm_prompt_builders-0.3.0.dist-info/licenses/LICENSE
llm_prompt_builders-0.3.0.dist-info/RECORD
