Metadata-Version: 2.4
Name: llm_prompt_builders
Version: 0.3.0
Summary: Composable prompt-engineering toolkit with roles, contexts, templates, and accelerators
Project-URL: Homepage, https://github.com/OHDSI/llm_prompt_builders/
Project-URL: Documentation, https://github.com/OHDSI/llm_prompt_builders/wiki
Project-URL: Source, https://github.com/OHDSI/llm_prompt_builders
Project-URL: Tracker, https://github.com/OHDSI/llm_prompt_builders/issues
Author-email: Gowtham Rao <rao@ohdsi.org>
Maintainer-email: Gowtham Rao <rao@ohdsi.org>
License:                                  Apache License
License-File: LICENSE
Keywords: LLM,composable,prompt-engineering,prompts
Classifier: Development Status :: 4 - Beta
Classifier: License :: OSI Approved :: Apache Software License
Classifier: Programming Language :: Python :: 3
Classifier: Programming Language :: Python :: 3.9
Classifier: Programming Language :: Python :: 3.10
Classifier: Programming Language :: Python :: 3.11
Classifier: Topic :: Software Development :: Libraries
Requires-Python: >=3.9
Requires-Dist: openai>=0.27.0
Requires-Dist: pydantic>=1.8.2
Provides-Extra: dev
Requires-Dist: black; extra == 'dev'
Requires-Dist: coverage[toml]; extra == 'dev'
Requires-Dist: pre-commit; extra == 'dev'
Requires-Dist: pytest-cov; extra == 'dev'
Requires-Dist: pytest>=8.1; extra == 'dev'
Requires-Dist: ruff; extra == 'dev'
